[
    {
        "time": 4.80,
        "x": -2, 
        "y": 0,
        "rotation": 270
    },
    {
        "time": 5.836,
        "x": 2, 
        "y": 0,
        "rotation": 90
    },
    {
        "time": 6.862,
        "x": 0, 
        "y": -3,
        "rotation": 0
    },
    {
        "time": 8.888,
        "x": 3, 
        "y": 3,
        "rotation": 90
    },
    {
        "time": 9.924,
        "x": -3, 
        "y": 3,
        "rotation": 270
    },
    {
        "time": 10.950,
        "x": 0, 
        "y": 2,
        "rotation": 180
    },
    {
        "time": 11.707,
        "x": 0, 
        "y": -2,
        "rotation": 0
    },
    {
        "time": 12.981,
        "x": 0, 
        "y": 3,
        "rotation": 180
    },
    {
        "time": 13.968,
        "x": 3, 
        "y": -3,
        "rotation": 30
    },
    {
        "time": 15.018,
        "x": -3, 
        "y": -3,
        "rotation": 330
    },
    {
        "time": 17.002,
        "x": 3, 
        "y": 0,
        "rotation": 90
    },
    {
        "time": 18.013,
        "x": -3, 
        "y": 0,
        "rotation": 270
    },
    {
        "time": 18.979,
        "x": 0, 
        "y": 3,
        "rotation": 180
    },
    {
        "time": 19.860,
        "x": 0, 
        "y": -3,
        "rotation": 0
    },
    {
        "time": 20.424,
        "x": -3, 
        "y": 3,
        "rotation": 225
    },
    {
        "time": 20.977,
        "x": 3, 
        "y": -3,
        "rotation": 45
    },
    {
        "time": 23.024,
        "x": 3, 
        "y": 3,
        "rotation": 135
    },
    {
        "time": 24.017,
        "x": -3, 
        "y": -3,
        "rotation": 315
    },
    {
        "time": 24.585,
        "x": 3, 
        "y": 0,
        "rotation": 135
    },
    {
        "time": 25.053,
        "x": 0, 
        "y": 3,
        "rotation": 225
    },
    {
        "time": 26.041,
        "x": -3, 
        "y": 0,
        "rotation": 315
    },
    {
        "time": 27.050,
        "x": 0, 
        "y": -3,
        "rotation": 45
    },
    {
        "time": 28.025,
        "x": -3, 
        "y": 3,
        "rotation": 270
    },
    {
        "time": 29.079,
        "x": 0, 
        "y": 2,
        "rotation": 180
    },
    {
        "time": 30.075,
        "x": 0, 
        "y": -2,
        "rotation": 0
    },
    {
        "time": 31.083,
        "x": 0, 
        "y": 3,
        "rotation": 180
    },
    {
        "time": 31.912,
        "x": 3, 
        "y": -3,
        "rotation": 30
    },
    {
        "time": 32.409,
        "x": -3, 
        "y": -3,
        "rotation": 330
    },
    {
        "time": 33.028,
        "x": 3, 
        "y": 0,
        "rotation": 90
    },
    {
        "time": 34.530,
        "x": -3, 
        "y": 0,
        "rotation": 270
    },
    {
        "time": 35.596,
        "x": 0, 
        "y": 3,
        "rotation": 180
    },
    {
        "time": 36.619,
        "x": 0, 
        "y": -3,
        "rotation": 0
    },
    {
        "time": 37.102,
        "x": -3, 
        "y": 3,
        "rotation": 225
    },
    {
        "time": 37.605,
        "x": 3, 
        "y": -3,
        "rotation": 45
    },
    {
        "time": 38.152,
        "x": 3, 
        "y": 3,
        "rotation": 135
    },
    {
        "time": 39.648,
        "x": -3, 
        "y": -3,
        "rotation": 315
    },
    {
        "time": 40.659,
        "x": 3, 
        "y": 0,
        "rotation": 135
    },
    {
        "time": 41.669,
        "x": 0, 
        "y": 3,
        "rotation": 225
    },
    {
        "time": 42.650,
        "x": -3, 
        "y": 0,
        "rotation": 315
    },
    {
        "time": 43.642,
        "x": 0, 
        "y": -3,
        "rotation": 45
    },
    {
        "time": 44.696,
        "x": -3, 
        "y": 3,
        "rotation": 270
    },
    {
        "time": 45.683,
        "x": 0, 
        "y": 2,
        "rotation": 180
    },
    {
        "time": 46.194,
        "x": 0, 
        "y": -2,
        "rotation": 0
    },
    {
        "time": 46.694,
        "x": 0, 
        "y": 3,
        "rotation": 180
    },
    {
        "time": 47.698,
        "x": 3, 
        "y": -3,
        "rotation": 30
    },
    {
        "time": 48.677,
        "x": -3, 
        "y": -3,
        "rotation": 330
    },
    {
        "time": 49.210,
        "x": 3, 
        "y": 0,
        "rotation": 90
    },
    {
        "time": 51.527,
        "x": -3, 
        "y": 0,
        "rotation": 270
    }
]